{"total_listings": 23051, "unique_vehicles": 3294, "manufacturers": 99, "avg_price": 589.86, "median_price": 500.0, "min_price": 0.0, "max_price": 15000.0, "avg_mileage": 159800.61, "top_manufacturers": {"Toyota": 5021, "Nissan": 2750, "Mazda": 2423, "Ford": 1652, "Honda": 1482, "Suzuki": 1334, "Holden": 1035, "Mitsubishi": 953, "Subaru": 838, "Volkswagen": 743}, "fuel_types": {"Petrol": 17205, "Diesel": 2679, "Hybrid": 2420, "Electric": 267, "LPG": 20, "Dual Fuel": 3}, "registration_status": {"No": 19580, "Yes": 3471}}